Metadata-Version: 2.1
Name: Webzer
Version: 1.3
Summary: Websites made easy.
Home-page: https://github.com/KodeyCode/Webzer
Download-URL: https://github.com/KodeyCode/Webzer/archive/v1.3.tar.gz
Author: LJDev
Author-email: lfwjohns@googlemail.com
License: MIT
Keywords: Web Module,EASY-TO-USE,Websites
Platform: UNKNOWN
Classifier: Development Status :: 5 - Production/Stable
Classifier: Intended Audience :: Developers
Classifier: Topic :: Software Development :: Build Tools
Classifier: License :: OSI Approved :: MIT License
Classifier: Programming Language :: Python :: 3.9
License-File: LICENSE
